blarify/__init__.py
blarify/agents/__init__.py
blarify/agents/api_key_manager.py
blarify/agents/llm_provider.py
blarify/agents/prompt_templates/__init__.py
blarify/agents/prompt_templates/api_documentation.py
blarify/agents/prompt_templates/base.py
blarify/agents/prompt_templates/component_analysis.py
blarify/agents/prompt_templates/component_documentation.py
blarify/agents/prompt_templates/component_identification.py
blarify/agents/prompt_templates/cross_component_analysis.py
blarify/agents/prompt_templates/documentation_consolidation.py
blarify/agents/prompt_templates/entry_point_discovery.py
blarify/agents/prompt_templates/framework_detection.py
blarify/agents/prompt_templates/function_with_calls_analysis.py
blarify/agents/prompt_templates/leaf_node_analysis.py
blarify/agents/prompt_templates/parent_node_analysis.py
blarify/agents/prompt_templates/relationship_extraction.py
blarify/agents/prompt_templates/spec_discovery.py
blarify/agents/prompt_templates/system_overview.py
blarify/agents/prompt_templates/template_manager.py
blarify/agents/rotating_provider/__init__.py
blarify/agents/rotating_provider/rotating_anthropic.py
blarify/agents/rotating_provider/rotating_google.py
blarify/agents/rotating_provider/rotating_openai.py
blarify/agents/rotating_provider/rotating_providers.py
blarify/agents/utils.py
blarify/cli/__init__.py
blarify/cli/commands/__init__.py
blarify/cli/commands/create.py
blarify/cli/main.py
blarify/cli/project_config.py
blarify/code_hierarchy/__init__.py
blarify/code_hierarchy/languages/FoundRelationshipScope.py
blarify/code_hierarchy/languages/__init__.py
blarify/code_hierarchy/languages/csharp_definitions.py
blarify/code_hierarchy/languages/fallback_definitions.py
blarify/code_hierarchy/languages/go_definitions.py
blarify/code_hierarchy/languages/java_definitions.py
blarify/code_hierarchy/languages/javascript_definitions.py
blarify/code_hierarchy/languages/language_definitions.py
blarify/code_hierarchy/languages/php_definitions.py
blarify-1.3.9.dist-info/LICENSE.md
blarify-1.3.9.dist-info/METADATA
blarify-1.3.9.dist-info/WHEEL
blarify-1.3.9.dist-info/entry_points.txt
blarify-1.3.9.dist-info/RECORD
