Metadata-Version: 2.3
Name: blarify
Version: 1.3.9
Summary: A simple graph builder based on LSP calls
License: MIT
Author: Juan Vargas
Author-email: juan@blar.io
Requires-Python: >=3.11,<=3.14
Classifier: License :: OSI Approved :: MIT License
Classifier: Programming Language :: Python :: 3
Classifier: Programming Language :: Python :: 3.11
Classifier: Programming Language :: Python :: 3.12
Classifier: Programming Language :: Python :: 3.13
Requires-Dist: asyncio (>=3.4.3,<4.0.0)
Requires-Dist: docker (>=7.1.0,<8.0.0)
Requires-Dist: falkordb (>=1.0.10,<2.0.0)
Requires-Dist: fastmcp (>=2.12.0,<3.0.0)
Requires-Dist: filelock (>=3.16.1,<4.0.0)
Requires-Dist: jedi-language-server (>=0.43.1,<0.44.0)
Requires-Dist: json-repair (>=0.47.7,<0.48.0)
Requires-Dist: langchain (>=0.3.26,<0.4.0)
Requires-Dist: langchain-anthropic (>=0.3.17,<0.4.0)
Requires-Dist: langchain-google-genai (>=2.1.7,<3.0.0)
Requires-Dist: langchain-openai (>=0.3.28,<0.4.0)
Requires-Dist: langgraph (>=0.5.2,<0.6.0)
Requires-Dist: neo4j (>=5.25.0,<6.0.0)
Requires-Dist: protobuf (==6.31.1)
Requires-Dist: psutil (>=7.0.0,<8.0.0)
Requires-Dist: python-dotenv (>=1.0.1,<2.0.0)
Requires-Dist: requests (>=2.32.3,<3.0.0)
Requires-Dist: rich (>=14.1.0,<15.0.0)
Requires-Dist: tree-sitter (>=0.23.2,<0.24.0)
Requires-Dist: tree-sitter-c-sharp (>=0.23.1,<0.24.0)
Requires-Dist: tree-sitter-go (>=0.23.4,<0.24.0)
Requires-Dist: tree-sitter-java (>=0.23.5,<0.24.0)
Requires-Dist: tree-sitter-javascript (>=0.23.0,<0.24.0)
Requires-Dist: tree-sitter-php (>=0.23.11,<0.24.0)
Requires-Dist: tree-sitter-python (>=0.23.2,<0.24.0)
Requires-Dist: tree-sitter-ruby (>=0.23.0,<0.24.0)
Requires-Dist: tree-sitter-typescript (>=0.23.2,<0.24.0)
Requires-Dist: typing-extensions (>=4.12.2,<5.0.0)
Requires-Dist: vendoring (>=1.2.0,<2.0.0)
Requires-Dist: websockets (>=13.1,<14.0)
Project-URL: Homepage, https://blar.io
Project-URL: Repository, https://github.com/blarApp/blarify
